{
  "timestamp": "20250825_193118",
  "datetime": "2025-08-25 19:31:18",
  "photo_path": "photos/20250825_193117.jpg",
  "result_image_path": "photos/food_record_20250825_193118.jpg",
  "dish_name": "麻婆豆腐",
  "confidence": 0.6690117716789246,
  "nutrients": {
    "????(kcal)": 72.8633495182544,
    "??????(g)": 10.308631270900367,
    "???(g)": 595.4411155346036,
    "????????(g)": 7.374777798354626,
    "?????A(??g)": 6.04831005461514,
    "?????B1(mg)": 1.179619499966502,
    "?????B2(mg)": 14.331865788698197,
    "?????B6(mg)": 1.6910724230110645,
    "?????B12(??g)": 22.62136430196464,
    "?????C(mg)": 10.808516956865788,
    "?????D(??g)": 2.5825452242046594,
    "?????E(mg)": 0.10341944545507431,
    "?????K(??g)": 0.06867763936519623,
    "??(mg)": 735.3057989460975,
    "??(??g)": 0.8327449230849743,
    "?(mg)": 142.2744190566242
  },
  "detection_type": "food_record",
  "total_detected": 2,
  "has_gesture": false,
  "gesture_selected": false,
  "full_result": {
    "food_detections": [
      {
        "dish_name": "红烧肉",
        "confidence": 0.6600965857505798,
        "bbox": [
          29,
          186,
          466,
          475
        ],
        "yolo_class": "orange"
      },
      {
        "dish_name": "麻婆豆腐",
        "confidence": 0.6690117716789246,
        "bbox": [
          395,
          269,
          1013,
          710
        ],
        "yolo_class": "orange"
      }
    ]
  }
}